nxtbrick
