Metadata-Version: 1.1
Name: scratch-nxt-extension
Version: 0.0.3
Summary: Provides a http helper app to allow Scratch 2 to control a LEGO NXT brick
Home-page: http://mrproctor.net/scratch
Author: Chris Proctor
Author-email: chris.proctor@gmail.com
License: UNKNOWN
Platform: UNKNOWN
Classifier: Programming Language :: Python
Classifier: Programming Language :: Python :: 2
Classifier: License :: OSI Approved :: MIT License
Classifier: Operating System :: MacOS :: MacOS X
Classifier: Environment :: Console
Classifier: Intended Audience :: Education
Classifier: Topic :: Education
